tts_webui_extension/bark/BarkModelManager.py
tts_webui_extension/bark/BarkParams.py
tts_webui_extension/bark/FullGeneration.py
tts_webui_extension/bark/__init__.py
tts_webui_extension/bark/bark_config.py
tts_webui_extension/bark/bark_tab.py
tts_webui_extension/bark/create_voice_string.py
tts_webui_extension/bark/demo.py
tts_webui_extension/bark/extended_generate.py
tts_webui_extension/bark/generate_and_save_metadata.py
tts_webui_extension/bark/generate_random_seed.py
tts_webui_extension/bark/generation_settings.py
tts_webui_extension/bark/get_audio_from_npz.py
tts_webui_extension/bark/get_bark_voice_hash.py
tts_webui_extension/bark/get_speaker_gender.py
tts_webui_extension/bark/history_to_hash.py
tts_webui_extension/bark/log_generation.py
tts_webui_extension/bark/main.py
tts_webui_extension/bark/npz_tools.py
tts_webui_extension/bark/parse_or_set_seed.py
tts_webui_extension/bark/settings_tab_bark.py
tts_webui_extension/bark/split_text_functions.py
tts_webui_extension/bark/vocos_tab_bark.py
tts_webui_extension/bark/model_loader/__init__.py
tts_webui_extension/bark/model_loader/convert_model.py
tts_webui_extension/bark/model_loader/loader.py
tts_webui_extension/bark/voices/__init__.py
tts_webui_extension/bark/voices/edit_metadata_ui.py
tts_webui_extension/bark/voices/get_hash_memoized.py
tts_webui_extension/bark/voices/get_npz_files_voices.py
tts_webui_extension/bark/voices/save_photo.py
tts_webui_extension/bark/voices/voices_tab.py
tts_webui_extension_bark-1.1.0.dist-info/licenses/LICENSE
tts_webui_extension_bark-1.1.0.dist-info/METADATA
tts_webui_extension_bark-1.1.0.dist-info/WHEEL
tts_webui_extension_bark-1.1.0.dist-info/top_level.txt
tts_webui_extension_bark-1.1.0.dist-info/RECORD
