Metadata-Version: 2.4
Name: tts_webui_extension.bark
Version: 1.1.0
Summary: A Bark: A text-to-speech model extension for TTS Generation WebUI
Author: rsxdalv
Project-URL: Homepage, https://github.com/rsxdalv/tts_webui_extension.bark
Classifier: Programming Language :: Python :: 3
Classifier: License :: OSI Approved :: MIT License
Classifier: Operating System :: OS Independent
Requires-Python: >=3.7
License-File: LICENSE
Requires-Dist: tts-webui.bark
Dynamic: license-file
